LICENSE.txt
MANIFEST.in
README.rst
setup.py
kd_samba/__init__.py
kd_samba.egg-info/PKG-INFO
kd_samba.egg-info/SOURCES.txt
kd_samba.egg-info/dependency_links.txt
kd_samba.egg-info/requires.txt
kd_samba.egg-info/top_level.txt
kd_samba/static/.placeholder
kd_samba/templates/.placeholder