Metadata-Version: 1.2
Name: kd-samba
Version: 0.1.dev0
Summary: Web interface for managing samba users
Home-page: https://gitlab.com/kamedata/py_samba_gui
Author: Federico Campoli
Author-email: thedoctor@pgdba.org
Maintainer: Federico Campoli
Maintainer-email: thedoctor@pgdba.org
License: BSD License
Keywords: samba
Platform: linux
Classifier: License :: OSI Approved :: BSD License
Classifier: Environment :: Console
Classifier: Intended Audience :: Developers
Classifier: Intended Audience :: Information Technology
Classifier: Intended Audience :: System Administrators
Classifier: Natural Language :: English
Classifier: Operating System :: POSIX :: BSD
Classifier: Operating System :: POSIX :: Linux
Classifier: Programming Language :: Python
Classifier: Programming Language :: Python :: 3
Classifier: Programming Language :: Python :: 3.5
Classifier: Programming Language :: Python :: 3.6
Classifier: Topic :: Database :: Database Engines/Servers
Classifier: Topic :: Other/Nonlisted Topic
Requires-Python: >=3.7
